arbitragelab/__init__.py
arbitragelab/codependence/__init__.py
arbitragelab/codependence/codependence_matrix.py
arbitragelab/codependence/correlation.py
arbitragelab/codependence/gnpr_distance.py
arbitragelab/codependence/information.py
arbitragelab/codependence/optimal_transport.py
arbitragelab/cointegration_approach/__init__.py
arbitragelab/cointegration_approach/base.py
arbitragelab/cointegration_approach/coint_sim.py
arbitragelab/cointegration_approach/engle_granger.py
arbitragelab/cointegration_approach/johansen.py
arbitragelab/cointegration_approach/minimum_profit.py
arbitragelab/cointegration_approach/multi_coint.py
arbitragelab/cointegration_approach/sparse_mr_portfolio.py
arbitragelab/cointegration_approach/utils.py
arbitragelab/copula_approach/__init__.py
arbitragelab/copula_approach/archimedean/__init__.py
arbitragelab/copula_approach/archimedean/clayton.py
arbitragelab/copula_approach/archimedean/frank.py
arbitragelab/copula_approach/archimedean/gumbel.py
arbitragelab/copula_approach/archimedean/joe.py
arbitragelab/copula_approach/archimedean/n13.py
arbitragelab/copula_approach/archimedean/n14.py
arbitragelab/copula_approach/base.py
arbitragelab/copula_approach/copula_calculation.py
arbitragelab/copula_approach/elliptical/__init__.py
arbitragelab/copula_approach/elliptical/gaussian.py
arbitragelab/copula_approach/elliptical/student.py
arbitragelab/copula_approach/mixed_copulas/__init__.py
arbitragelab/copula_approach/mixed_copulas/base.py
arbitragelab/copula_approach/mixed_copulas/cfg_mix_copula.py
arbitragelab/copula_approach/mixed_copulas/ctg_mix_copula.py
arbitragelab/copula_approach/pairs_selection.py
arbitragelab/copula_approach/vine_copula_partner_selection.py
arbitragelab/copula_approach/vine_copula_partner_selection_utils.py
arbitragelab/copula_approach/vinecop_generate.py
arbitragelab/copula_approach/vinecop_strategy.py
arbitragelab/distance_approach/__init__.py
arbitragelab/distance_approach/basic_distance_approach.py
arbitragelab-1.0.0.dist-info/LICENSE.txt
arbitragelab-1.0.0.dist-info/METADATA
arbitragelab-1.0.0.dist-info/WHEEL
arbitragelab-1.0.0.dist-info/RECORD
