Metadata-Version: 2.1
Name: arbitragelab
Version: 1.0.0
Summary: ArbitrageLab is a collection of algorithms from the best academic journals and graduate-level textbooks, which focuses on the branch of statistical arbitrage known as pairs trading. We have extended the implementations to include the latest methods that trade a portfolio of n-assets (mean-reverting portfolios).
Home-page: https://www.hudsonthames.org/
License: BSD-3-Clause
Keywords: arbitrage,finance,investment,education,trading
Author: Hudson and Thames Quantitative Research
Author-email: opensource@hudsonthames.org
Requires-Python: >=3.8,<4.0
Classifier: Development Status :: 5 - Production/Stable
Classifier: Intended Audience :: Developers
Classifier: Intended Audience :: Education
Classifier: Intended Audience :: Financial and Insurance Industry
Classifier: Intended Audience :: Science/Research
Classifier: License :: OSI Approved :: BSD License
Classifier: Operating System :: OS Independent
Classifier: Programming Language :: Python :: 3
Classifier: Programming Language :: Python :: 3.8
Classifier: Programming Language :: Python :: 3.9
Classifier: Programming Language :: Python :: 3.10
Classifier: Programming Language :: Python :: 3.11
Classifier: Programming Language :: Python :: 3.12
Classifier: Topic :: Office/Business :: Financial :: Investment
Classifier: Topic :: Scientific/Engineering
Classifier: Topic :: Scientific/Engineering :: Artificial Intelligence
Provides-Extra: docs
Provides-Extra: tests
Requires-Dist: POT (==0.9.0)
Requires-Dist: arch (==5.5.0)
Requires-Dist: cvxpy (==1.4.3) ; python_version >= "3.10" and python_version < "4"
Requires-Dist: cvxpy (==1.4.3) ; sys_platform != "darwin" and python_version >= "3.8" and python_version < "3.10" or platform_machine != "arm64" and python_version >= "3.8" and python_version < "3.10"
Requires-Dist: cython (==0.29.28)
Requires-Dist: dash (==2.10.2)
Requires-Dist: jupyter-dash (>=0.2.0,<1.0.0)
Requires-Dist: keras (==2.13.1) ; python_version >= "3.8" and python_version < "3.12"
Requires-Dist: keras (==3.0.0) ; python_version >= "3.12" and python_version < "4"
Requires-Dist: lxml (>=4.9.1,<5.0.0)
Requires-Dist: matplotlib (==3.7.1) ; python_version >= "3.8" and python_version < "3.12"
Requires-Dist: matplotlib (==3.8.4) ; python_version >= "3.12" and python_version < "4"
Requires-Dist: mpmath (==1.2.1)
Requires-Dist: networkx (>=2.2,<2.6)
Requires-Dist: numpy (==1.23.5) ; python_version >= "3.8" and python_version < "3.12"
Requires-Dist: numpy (==1.26.4) ; python_version >= "3.12" and python_version < "4"
Requires-Dist: pandas (==2.0.0)
Requires-Dist: pmdarima (==2.0.4)
Requires-Dist: protobuf (>=3.20.3)
Requires-Dist: pyvinecopulib (==0.6.5)
Requires-Dist: pyzmq (==26.0.0)
Requires-Dist: requests_html (==0.10.0)
Requires-Dist: scikit-learn (==1.1.3) ; python_version >= "3.8" and python_version < "3.12"
Requires-Dist: scikit-learn (==1.3.0) ; python_version >= "3.12" and python_version < "4"
Requires-Dist: scipy (==1.10.1) ; python_version >= "3.8" and python_version < "3.9"
Requires-Dist: scipy (==1.11.0) ; python_version >= "3.9" and python_version < "3.10"
Requires-Dist: scipy (==1.12.0) ; python_version >= "3.10" and python_version < "4"
Requires-Dist: seaborn (==0.12.2)
Requires-Dist: statsmodels (==0.14.0)
Requires-Dist: tensorflow (==2.13.0) ; sys_platform != "darwin" and python_version >= "3.8" and python_version < "3.12" or platform_machine != "arm64" and python_version >= "3.8" and python_version < "3.12"
Requires-Dist: tensorflow (==2.16.1) ; sys_platform != "darwin" and python_version >= "3.12" and python_version < "4" or platform_machine != "x86_64" and python_version >= "3.12" and python_version < "4"
Requires-Dist: tensorflow-io-gcs-filesystem (==0.34.0) ; sys_platform != "darwin" and python_version >= "3.8" and python_version < "3.12" or platform_machine != "arm64" and python_version >= "3.8" and python_version < "3.12"
Requires-Dist: tensorflow-macos (==2.13.0) ; sys_platform == "darwin" and platform_machine == "arm64" and python_version >= "3.8" and python_version < "3.12"
Requires-Dist: tensorflow-macos (==2.16.1) ; sys_platform == "darwin" and platform_machine == "x86_64" and python_version >= "3.12" and python_version < "4"
Requires-Dist: werkzeug (==2.2.3)
Requires-Dist: wrapt (==1.14.0) ; python_version >= "3.8" and python_version < "3.12"
Requires-Dist: yahoo-fin (==0.8.9.1)
Requires-Dist: yfinance (==0.2.37)
Project-URL: Apprenticeship Program, https://hudsonthames.org/apprenticeship-program/
Project-URL: Bug Reports, https://github.com/hudson-and-thames/arbitragelab/issues
Project-URL: Blog, https://hudsonthames.org/blog/
Project-URL: Documentation, https://hudson-and-thames-arbitragelab.readthedocs-hosted.com/en/latest/index.html
Project-URL: Repository, https://github.com/hudson-and-thames/arbitragelab
